LICENSE
MANIFEST.in
README.md
setup.cfg
setup.py
a99/__init__.py
a99/astropyaux.py
a99/config.py
a99/conversion.py
a99/cryptography.py
a99/datetimefunc.py
a99/debugging.py
a99/fileio.py
a99/introspection.py
a99/litedb.py
a99/loggingaux.py
a99/matplotlibaux.py
a99/misc.py
a99/parts.py
a99/search.py
a99/textinterface.py
a99.egg-info/PKG-INFO
a99.egg-info/SOURCES.txt
a99.egg-info/dependency_links.txt
a99.egg-info/top_level.txt
a99/gui/__init__.py
a99/gui/_logpart.py
a99/gui/a_WBase.py
a99/gui/a_WCollapsiblePanel.py
a99/gui/a_WConfigEditor.py
a99/gui/a_WDBRegistry.py
a99/gui/a_WEditor.py
a99/gui/a_WParametersEditor.py
a99/gui/a_WSelectFileOrDir.py
a99/gui/a_XLogDialog.py
a99/gui/a_XLogMainWindow.py
a99/gui/a_XParametersEditor.py
a99/gui/errorcollector.py
a99/gui/parameter.py
a99/gui/syntax.py
a99/gui/ui_XParametersEditor.py
a99/gui/xmisc.py
a99/icons/README.txt
a99/icons/add-files-to-archive.png
a99/icons/add-folder-to-archive.png
a99/icons/alien.png
a99/icons/application-exit.png
a99/icons/appointment-new.png
a99/icons/bookmark-new.png
a99/icons/call-start.png
a99/icons/call-stop.png
a99/icons/chart1.png
a99/icons/chart2.png
a99/icons/contact-new.png
a99/icons/dialog-apply.png
a99/icons/dialog-ok.png
a99/icons/document-export.png
a99/icons/document-import.png
a99/icons/document-new.png
a99/icons/document-open-recent.png
a99/icons/document-open.png
a99/icons/document-page-setup.png
a99/icons/document-print-preview.png
a99/icons/document-print.png
a99/icons/document-properties.png
a99/icons/document-revert.png
a99/icons/document-save-as.png
a99/icons/document-save.png
a99/icons/document-send.png
a99/icons/edit-clear.png
a99/icons/edit-copy.png
a99/icons/edit-cut.png
a99/icons/edit-find-replace.png
a99/icons/edit-find.png
a99/icons/edit-paste.png
a99/icons/edit-redo.png
a99/icons/edit-select-all.png
a99/icons/edit-undo.png
a99/icons/extract-archive.png
a99/icons/folder-change.png
a99/icons/folder-copy.png
a99/icons/folder-move.png
a99/icons/folder-new.png
a99/icons/format-indent-less.png
a99/icons/format-indent-more.png
a99/icons/format-justify-center.png
